odoo/addons/account-view-vat-move-line/__init__.py
odoo/addons/account-view-vat-move-line/__manifest__.py
odoo/addons/account-view-vat-move-line/models/__init__.py
odoo/addons/account-view-vat-move-line/models/account_move_line.py
odoo/addons/account-view-vat-move-line/views/account_move_line_views.xml
odoo14_addon_account_view_vat_move_line-14.0.0.0.2.dist-info/METADATA
odoo14_addon_account_view_vat_move_line-14.0.0.0.2.dist-info/WHEEL
odoo14_addon_account_view_vat_move_line-14.0.0.0.2.dist-info/top_level.txt
odoo14_addon_account_view_vat_move_line-14.0.0.0.2.dist-info/RECORD
